 {"data": {
    "coord": {
        "lon": 36.8167,
        "lat": -1.2833
    },
    "weather": [
        {
            "id": 803,
            "main": "Clouds",
            "description": "broken clouds",
            "icon": "04d"
        }
    ],
    "base": "stations",
    "main": {
        "temp": 288.96,
        "feels_like": 288.97,
        "temp_min": 287.58,
        "temp_max": 289.08,
        "pressure": 1021,
        "humidity": 91
    },
    "visibility": 10000,
    "wind": {
        "speed": 1.03,
        "deg": 0
    },
    "clouds": {
        "all": 75
    },
    "dt": 1670989892,
    "sys": {
        "type": 1,
        "id": 2558,
        "country": "KE",
        "sunrise": 1670988092,
        "sunset": 1671031990
    },
    "timezone": 10800,
    "id": 184745,
    "name": "Nairobi",
    "cod": 200
 

}
}